<?xml version = '1.0' encoding = 'UTF-8'?>
<TableProxyOraclev12c class="oracle.dbtools.crest.model.design.storage.oracle.v12c.TableProxyOraclev12c" name="ALBUM" directorySegmentName="seg_0" id="3D8B4029-4A6A-31CC-94E2-FD97AD11A779">
<createdBy>andre</createdBy>
<createdTime>2018-07-06 18:09:26 UTC</createdTime>
<ownerDesignName>erd</ownerDesignName>
<schemaObject>BF8D4D3C-C230-A18C-AAE5-514E33CA7B35</schemaObject>
<logging>YES</logging>
<partitionedRowMovement>DISABLE</partitionedRowMovement>
<segment>965AD8A6-477F-7CB4-D1DF-0F7358417BCA</segment>
<tableSpace>BBE208F0-22D4-D22C-0C07-FBA509FAC116</tableSpace>
<temporaryChanged>false</temporaryChanged>
<accessDriverType>oracle_loader</accessDriverType>
<rejectLimit></rejectLimit>
<inMemory>NO</inMemory>
<columnProxies itemClass="oracle.dbtools.crest.model.design.storage.oracle.v12c.ColumnProxyOraclev12c">
<ColumnProxy name="ALBUMID" id="6C6D9119-2C68-7A81-2FD6-E311999D2E9D">
<createdBy>andre</createdBy>
<createdTime>2018-07-06 18:09:27 UTC</createdTime>
<ownerDesignName>erd</ownerDesignName>
</ColumnProxy>
<ColumnProxy name="ARTISTID" id="76CB6750-B6E1-CDA9-504B-283363602859">
<createdBy>andre</createdBy>
<createdTime>2018-07-06 18:09:27 UTC</createdTime>
<ownerDesignName>erd</ownerDesignName>
</ColumnProxy>
<ColumnProxy name="TITLE" id="BEE4FA80-6DC6-6BC6-33DF-E3A700E9CCF1">
<createdBy>andre</createdBy>
<createdTime>2018-07-06 18:09:27 UTC</createdTime>
<ownerDesignName>erd</ownerDesignName>
</ColumnProxy>
</columnProxies>
<indexProxies>
<IndexProxy class="oracle.dbtools.crest.model.design.storage.oracle.v10g.IndexProxyOraclev10g" name="PK_ALBUM" id="9205E4A6-BE54-32EF-EB96-DC7C0C1DED17">
<createdBy>andre</createdBy>
<createdTime>2018-07-06 18:09:28 UTC</createdTime>
<ownerDesignName>erd</ownerDesignName>
<schemaObject>BF8D4D3C-C230-A18C-AAE5-514E33CA7B35</schemaObject>
<segment>9372BB5A-1F84-11DE-6345-8CC3CA6723AE</segment>
<tableSpace>BBE208F0-22D4-D22C-0C07-FBA509FAC116</tableSpace>
</IndexProxy>
</indexProxies>
<foreignKeys>
<ForeignKey class="oracle.dbtools.crest.model.design.storage.oracle.v10g.FKProxyOraclev10g" name="FK_ALBUMARTISTID" id="37855857-D67B-75C8-1EC9-5D52295F6753">
<createdBy>andre</createdBy>
<createdTime>2018-07-06 18:09:31 UTC</createdTime>
<ownerDesignName>erd</ownerDesignName>
</ForeignKey>
</foreignKeys>
<primaryKeys>
<PrimaryKey class="oracle.dbtools.crest.model.design.storage.oracle.v10g.PKProxyOraclev10g" name="PK_ALBUM" id="0011FBD2-7E3B-B2DC-CED5-D0DE9AB1EF5B">
<createdBy>andre</createdBy>
<createdTime>2018-07-06 18:09:29 UTC</createdTime>
<ownerDesignName>erd</ownerDesignName>
<segment>9372BB5A-1F84-11DE-6345-8CC3CA6723AE</segment>
<tableSpace>BBE208F0-22D4-D22C-0C07-FBA509FAC116</tableSpace>
<existingIndex>9205E4A6-BE54-32EF-EB96-DC7C0C1DED17</existingIndex>
<indexSegment>9372BB5A-1F84-11DE-6345-8CC3CA6723AE</indexSegment>
<indexSort>SORTED</indexSort>
<usingIndex>BY INDEX NAME</usingIndex>
</PrimaryKey>
</primaryKeys>
</TableProxyOraclev12c>